{
  "date" : "Tue, 09 Jun, 2026 15:42:49 +0000",
  "doco" : "For each file: start is seconds after start activity occurred. Length = milliseconds activity took",
  "files" : [{
    "name" : "/fsh-generated/resources/ImplementationGuide-ans.fhir.fr.test.ror.json",
    "size" : 36560,
    "processes" : [{
      "activity" : "load",
      "start" : 57,
      "length" : 1
    },
    {
      "activity" : "load",
      "start" : 58,
      "length" : 183
    },
    {
      "activity" : "checkR4R4B",
      "start" : 59,
      "length" : 25
    },
    {
      "activity" : "generateNarratives",
      "start" : 59,
      "length" : 95
    },
    {
      "activity" : "validate",
      "start" : 84,
      "length" : 2438
    },
    {
      "activity" : "checkConformanceResources3",
      "start" : 86,
      "length" : 1
    },
    {
      "activity" : "scanForUsageStats",
      "start" : 86,
      "length" : 2
    },
    {
      "activity" : "validate",
      "start" : 86,
      "length" : 1
    },
    {
      "activity" : "generate1",
      "start" : 86,
      "length" : 188
    },
    {
      "activity" : "generate2",
      "start" : 95,
      "length" : 405
    },
    {
      "activity" : "generateValidationPack",
      "start" : 126,
      "length" : 14
    }]
  },
  {
    "name" : "fsh-generated/resources/StructureDefinition-ror-activite-operationnelle.json",
    "size" : 3641,
    "processes" : [{
      "activity" : "loadResources",
      "start" : 57,
      "length" : 3
    },
    {
      "activity" : "load",
      "start" : 58,
      "length" : 5
    },
    {
      "activity" : "generateSnapshots",
      "start" : 58,
      "length" : 12
    },
    {
      "activity" : "load-configure",
      "start" : 59,
      "length" : 1
    },
    {
      "activity" : "generateNarratives",
      "start" : 59,
      "length" : 66
    },
    {
      "activity" : "validate",
      "start" : 63,
      "length" : 1
    },
    {
      "activity" : "validate",
      "start" : 67,
      "length" : 117
    },
    {
      "activity" : "checkConformanceResources",
      "start" : 86,
      "length" : 1
    },
    {
      "activity" : "generate1",
      "start" : 87,
      "length" : 44
    },
    {
      "activity" : "generate2",
      "start" : 96,
      "length" : 687
    },
    {
      "activity" : "generate2",
      "start" : 106,
      "length" : 184
    },
    {
      "activity" : "makeDependencies",
      "start" : 109,
      "length" : 1
    },
    {
      "activity" : "generateValidationPack",
      "start" : 126,
      "length" : 2
    }]
  },
  {
    "name" : "fsh-generated/resources/StructureDefinition-ror-capacite-accueil-operationnelle.json",
    "size" : 7951,
    "processes" : [{
      "activity" : "loadResources",
      "start" : 57,
      "length" : 3
    },
    {
      "activity" : "load",
      "start" : 58,
      "length" : 6
    },
    {
      "activity" : "generateSnapshots",
      "start" : 58,
      "length" : 17
    },
    {
      "activity" : "generateNarratives",
      "start" : 60,
      "length" : 31
    },
    {
      "activity" : "validate",
      "start" : 67,
      "length" : 179
    },
    {
      "activity" : "validate",
      "start" : 86,
      "length" : 1
    },
    {
      "activity" : "generate1",
      "start" : 87,
      "length" : 81
    },
    {
      "activity" : "generate2",
      "start" : 96,
      "length" : 270
    },
    {
      "activity" : "generate2",
      "start" : 106,
      "length" : 95
    },
    {
      "activity" : "generateValidationPack",
      "start" : 126,
      "length" : 3
    },
    {
      "activity" : "scanExamplesForR5",
      "start" : 140,
      "length" : 1
    }]
  },
  {
    "name" : "fsh-generated/resources/StructureDefinition-ror-capacite-habitation.json",
    "size" : 2154,
    "processes" : [{
      "activity" : "loadResources",
      "start" : 57,
      "length" : 1
    },
    {
      "activity" : "load",
      "start" : 58,
      "length" : 5
    },
    {
      "activity" : "generateSnapshots",
      "start" : 58,
      "length" : 10
    },
    {
      "activity" : "load-configure",
      "start" : 59,
      "length" : 1
    },
    {
      "activity" : "generateNarratives",
      "start" : 60,
      "length" : 11
    },
    {
      "activity" : "validate",
      "start" : 67,
      "length" : 37
    },
    {
      "activity" : "generate1",
      "start" : 87,
      "length" : 43
    },
    {
      "activity" : "generate2",
      "start" : 96,
      "length" : 172
    },
    {
      "activity" : "generate2",
      "start" : 107,
      "length" : 60
    },
    {
      "activity" : "generateValidationPack",
      "start" : 126,
      "length" : 2
    }]
  },
  {
    "name" : "fsh-generated/resources/StructureDefinition-ror-capacite-prise-charge.json",
    "size" : 2691,
    "processes" : [{
      "activity" : "loadResources",
      "start" : 57,
      "length" : 2
    },
    {
      "activity" : "load",
      "start" : 58,
      "length" : 4
    },
    {
      "activity" : "generateSnapshots",
      "start" : 58,
      "length" : 9
    },
    {
      "activity" : "generateNarratives",
      "start" : 60,
      "length" : 7
    },
    {
      "activity" : "validate",
      "start" : 68,
      "length" : 40
    },
    {
      "activity" : "checkConformanceResources",
      "start" : 86,
      "length" : 1
    },
    {
      "activity" : "scanForUsageStats",
      "start" : 86,
      "length" : 1
    },
    {
      "activity" : "generate1",
      "start" : 87,
      "length" : 36
    },
    {
      "activity" : "generate2",
      "start" : 97,
      "length" : 177
    },
    {
      "activity" : "generate2",
      "start" : 107,
      "length" : 47
    },
    {
      "activity" : "generateValidationPack",
      "start" : 126,
      "length" : 1
    }]
  },
  {
    "name" : "fsh-generated/resources/StructureDefinition-ror-capacite-savoir-faire.json",
    "size" : 1536,
    "processes" : [{
      "activity" : "loadResources",
      "start" : 57,
      "length" : 1
    },
    {
      "activity" : "load",
      "start" : 58,
      "length" : 3
    },
    {
      "activity" : "generateSnapshots",
      "start" : 58,
      "length" : 11
    },
    {
      "activity" : "generateNarratives",
      "start" : 60,
      "length" : 6
    },
    {
      "activity" : "validate",
      "start" : 68,
      "length" : 1729
    },
    {
      "activity" : "checkConformanceResources3",
      "start" : 86,
      "length" : 1
    },
    {
      "activity" : "validate",
      "start" : 86,
      "length" : 1
    },
    {
      "activity" : "generate1",
      "start" : 87,
      "length" : 31
    },
    {
      "activity" : "generate2",
      "start" : 97,
      "length" : 154
    },
    {
      "activity" : "generate2",
      "start" : 107,
      "length" : 41
    },
    {
      "activity" : "generateValidationPack",
      "start" : 126,
      "length" : 1
    },
    {
      "activity" : "scanProfilesForR5",
      "start" : 140,
      "length" : 1
    }]
  },
  {
    "name" : "fsh-generated/resources/StructureDefinition-ror-competence-exclusive.json",
    "size" : 1531,
    "processes" : [{
      "activity" : "loadResources",
      "start" : 57,
      "length" : 1
    },
    {
      "activity" : "load",
      "start" : 58,
      "length" : 3
    },
    {
      "activity" : "generateSnapshots",
      "start" : 58,
      "length" : 9
    },
    {
      "activity" : "generateNarratives",
      "start" : 60,
      "length" : 7
    },
    {
      "activity" : "validate",
      "start" : 69,
      "length" : 38
    },
    {
      "activity" : "generate1",
      "start" : 87,
      "length" : 33
    },
    {
      "activity" : "generate2",
      "start" : 97,
      "length" : 150
    },
    {
      "activity" : "generate2",
      "start" : 107,
      "length" : 39
    },
    {
      "activity" : "generateValidationPack",
      "start" : 126,
      "length" : 1
    }]
  },
  {
    "name" : "fsh-generated/resources/StructureDefinition-ror-competence.json",
    "size" : 1421,
    "processes" : [{
      "activity" : "loadResources",
      "start" : 57,
      "length" : 1
    },
    {
      "activity" : "load",
      "start" : 58,
      "length" : 3
    },
    {
      "activity" : "generateSnapshots",
      "start" : 58,
      "length" : 10
    },
    {
      "activity" : "generateNarratives",
      "start" : 60,
      "length" : 6
    },
    {
      "activity" : "validate",
      "start" : 69,
      "length" : 36
    },
    {
      "activity" : "checkConformanceResources",
      "start" : 86,
      "length" : 1
    },
    {
      "activity" : "generate1",
      "start" : 87,
      "length" : 29
    },
    {
      "activity" : "generate2",
      "start" : 97,
      "length" : 143
    },
    {
      "activity" : "generate2",
      "start" : 107,
      "length" : 37
    },
    {
      "activity" : "generateValidationPack",
      "start" : 126,
      "length" : 1
    }]
  },
  {
    "name" : "fsh-generated/resources/StructureDefinition-ror-desc-non-qualifiant.json",
    "size" : 1519,
    "processes" : [{
      "activity" : "loadResources",
      "start" : 57,
      "length" : 1
    },
    {
      "activity" : "load",
      "start" : 58,
      "length" : 2
    },
    {
      "activity" : "generateSnapshots",
      "start" : 58,
      "length" : 12
    },
    {
      "activity" : "generateNarratives",
      "start" : 60,
      "length" : 6
    },
    {
      "activity" : "validate",
      "start" : 69,
      "length" : 51
    },
    {
      "activity" : "validate",
      "start" : 86,
      "length" : 1
    },
    {
      "activity" : "generate1",
      "start" : 87,
      "length" : 32
    },
    {
      "activity" : "generate2",
      "start" : 97,
      "length" : 142
    },
    {
      "activity" : "generate2",
      "start" : 107,
      "length" : 37
    },
    {
      "activity" : "generateValidationPack",
      "start" : 126,
      "length" : 1
    }]
  },
  {
    "name" : "fsh-generated/resources/StructureDefinition-ror-droit-exercice-complementaire.json",
    "size" : 1664,
    "processes" : [{
      "activity" : "loadResources",
      "start" : 57,
      "length" : 1
    },
    {
      "activity" : "load",
      "start" : 58,
      "length" : 3
    },
    {
      "activity" : "generateSnapshots",
      "start" : 58,
      "length" : 10
    },
    {
      "activity" : "load-configure",
      "start" : 59,
      "length" : 1
    },
    {
      "activity" : "generateNarratives",
      "start" : 60,
      "length" : 7
    },
    {
      "activity" : "validate",
      "start" : 69,
      "length" : 49
    },
    {
      "activity" : "generate1",
      "start" : 87,
      "length" : 30
    },
    {
      "activity" : "generate2",
      "start" : 97,
      "length" : 169
    },
    {
      "activity" : "generate2",
      "start" : 107,
      "length" : 36
    },
    {
      "activity" : "generateValidationPack",
      "start" : 126,
      "length" : 2
    }]
  },
  {
    "name" : "fsh-generated/resources/StructureDefinition-ror-entite-geographique.json",
    "size" : 4935,
    "processes" : [{
      "activity" : "loadResources",
      "start" : 57,
      "length" : 2
    },
    {
      "activity" : "load",
      "start" : 58,
      "length" : 4
    },
    {
      "activity" : "generateSnapshots",
      "start" : 58,
      "length" : 48
    },
    {
      "activity" : "generateNarratives",
      "start" : 60,
      "length" : 2213
    },
    {
      "activity" : "validate",
      "start" : 69,
      "length" : 3990
    },
    {
      "activity" : "scanForUsageStats",
      "start" : 86,
      "length" : 1
    },
    {
      "activity" : "generate1",
      "start" : 87,
      "length" : 180
    },
    {
      "activity" : "generate2",
      "start" : 98,
      "length" : 451
    },
    {
      "activity" : "generate2",
      "start" : 107,
      "length" : 272
    },
    {
      "activity" : "generateValidationPack",
      "start" : 126,
      "length" : 7
    },
    {
      "activity" : "scanExamplesForR5",
      "start" : 140,
      "length" : 1
    }]
  },
  {
    "name" : "fsh-generated/resources/StructureDefinition-ror-entite-juridique.json",
    "size" : 3410,
    "processes" : [{
      "activity" : "loadResources",
      "start" : 57,
      "length" : 1
    },
    {
      "activity" : "load",
      "start" : 58,
      "length" : 5
    },
    {
      "activity" : "generateSnapshots",
      "start" : 58,
      "length" : 23
    },
    {
      "activity" : "generateNarratives",
      "start" : 62,
      "length" : 19
    },
    {
      "activity" : "validate",
      "start" : 73,
      "length" : 1165
    },
    {
      "activity" : "checkConformanceResources",
      "start" : 86,
      "length" : 1
    },
    {
      "activity" : "checkConformanceResources3",
      "start" : 86,
      "length" : 1
    },
    {
      "activity" : "validate",
      "start" : 86,
      "length" : 1
    },
    {
      "activity" : "generate1",
      "start" : 87,
      "length" : 91
    },
    {
      "activity" : "generate2",
      "start" : 98,
      "length" : 247
    },
    {
      "activity" : "generate2",
      "start" : 107,
      "length" : 110
    },
    {
      "activity" : "generateValidationPack",
      "start" : 126,
      "length" : 4
    }]
  },
  {
    "name" : "fsh-generated/resources/StructureDefinition-ror-equipement-specifique.json",
    "size" : 2193,
    "processes" : [{
      "activity" : "loadResources",
      "start" : 57,
      "length" : 1
    },
    {
      "activity" : "load",
      "start" : 58,
      "length" : 3
    },
    {
      "activity" : "generateSnapshots",
      "start" : 58,
      "length" : 15
    },
    {
      "activity" : "generateNarratives",
      "start" : 62,
      "length" : 9
    },
    {
      "activity" : "validate",
      "start" : 75,
      "length" : 570
    },
    {
      "activity" : "generate1",
      "start" : 87,
      "length" : 40
    },
    {
      "activity" : "generate2",
      "start" : 98,
      "length" : 143
    },
    {
      "activity" : "generate2",
      "start" : 107,
      "length" : 48
    },
    {
      "activity" : "generateValidationPack",
      "start" : 126,
      "length" : 2
    }]
  },
  {
    "name" : "fsh-generated/resources/StructureDefinition-ror-exercice-professionnel.json",
    "size" : 2711,
    "processes" : [{
      "activity" : "loadResources",
      "start" : 57,
      "length" : 2
    },
    {
      "activity" : "load",
      "start" : 58,
      "length" : 4
    },
    {
      "activity" : "generateSnapshots",
      "start" : 58,
      "length" : 25
    },
    {
      "activity" : "generateNarratives",
      "start" : 62,
      "length" : 17
    },
    {
      "activity" : "validate",
      "start" : 75,
      "length" : 4203
    },
    {
      "activity" : "validate",
      "start" : 86,
      "length" : 1
    },
    {
      "activity" : "generate1",
      "start" : 87,
      "length" : 70
    },
    {
      "activity" : "generate2",
      "start" : 98,
      "length" : 293
    },
    {
      "activity" : "generate2",
      "start" : 107,
      "length" : 111
    },
    {
      "activity" : "generateValidationPack",
      "start" : 126,
      "length" : 2
    }]
  },
  {
    "name" : "fsh-generated/resources/StructureDefinition-ror-forfait-socle-hebergement.json",
    "size" : 5410,
    "processes" : [{
      "activity" : "loadResources",
      "start" : 57,
      "length" : 1
    },
    {
      "activity" : "load",
      "start" : 58,
      "length" : 5
    },
    {
      "activity" : "generateSnapshots",
      "start" : 58,
      "length" : 17
    },
    {
      "activity" : "generateNarratives",
      "start" : 62,
      "length" : 11
    },
    {
      "activity" : "validate",
      "start" : 79,
      "length" : 34
    },
    {
      "activity" : "checkConformanceResources",
      "start" : 86,
      "length" : 1
    },
    {
      "activity" : "generate1",
      "start" : 87,
      "length" : 55
    },
    {
      "activity" : "generate2",
      "start" : 99,
      "length" : 155
    },
    {
      "activity" : "generate2",
      "start" : 107,
      "length" : 48
    },
    {
      "activity" : "generateValidationPack",
      "start" : 126,
      "length" : 1
    }]
  },
  {
    "name" : "fsh-generated/resources/StructureDefinition-ror-lieu-realisation-offre.json",
    "size" : 2338,
    "processes" : [{
      "activity" : "loadResources",
      "start" : 57,
      "length" : 1
    },
    {
      "activity" : "load",
      "start" : 58,
      "length" : 3
    },
    {
      "activity" : "generateSnapshots",
      "start" : 58,
      "length" : 9
    },
    {
      "activity" : "generateNarratives",
      "start" : 62,
      "length" : 9
    },
    {
      "activity" : "validate",
      "start" : 79,
      "length" : 23
    },
    {
      "activity" : "generate1",
      "start" : 87,
      "length" : 37
    },
    {
      "activity" : "generate2",
      "start" : 99,
      "length" : 137
    },
    {
      "activity" : "generate2",
      "start" : 107,
      "length" : 42
    },
    {
      "activity" : "generateValidationPack",
      "start" : 126,
      "length" : 1
    }]
  },
  {
    "name" : "fsh-generated/resources/StructureDefinition-ror-metadonnee.json",
    "size" : 4033,
    "processes" : [{
      "activity" : "loadResources",
      "start" : 57,
      "length" : 2
    },
    {
      "activity" : "load",
      "start" : 58,
      "length" : 4
    },
    {
      "activity" : "generateSnapshots",
      "start" : 58,
      "length" : 6
    },
    {
      "activity" : "generateNarratives",
      "start" : 62,
      "length" : 10
    },
    {
      "activity" : "validate",
      "start" : 79,
      "length" : 24
    },
    {
      "activity" : "checkConformanceResources3",
      "start" : 86,
      "length" : 1
    },
    {
      "activity" : "validate",
      "start" : 86,
      "length" : 1
    },
    {
      "activity" : "generate1",
      "start" : 87,
      "length" : 43
    },
    {
      "activity" : "generate2",
      "start" : 99,
      "length" : 140
    },
    {
      "activity" : "generate2",
      "start" : 107,
      "length" : 31
    },
    {
      "activity" : "generateValidationPack",
      "start" : 126,
      "length" : 1
    },
    {
      "activity" : "scanExamplesForR5",
      "start" : 140,
      "length" : 1
    }]
  },
  {
    "name" : "fsh-generated/resources/StructureDefinition-ror-offre-operationnelle.json",
    "size" : 6853,
    "processes" : [{
      "activity" : "loadResources",
      "start" : 57,
      "length" : 3
    },
    {
      "activity" : "load",
      "start" : 58,
      "length" : 6
    },
    {
      "activity" : "generateSnapshots",
      "start" : 58,
      "length" : 38
    },
    {
      "activity" : "loadDepInfo",
      "start" : 59,
      "length" : 1
    },
    {
      "activity" : "generateNarratives",
      "start" : 62,
      "length" : 26
    },
    {
      "activity" : "validate",
      "start" : 79,
      "length" : 602
    },
    {
      "activity" : "checkConformanceResources",
      "start" : 86,
      "length" : 1
    },
    {
      "activity" : "scanForUsageStats",
      "start" : 86,
      "length" : 1
    },
    {
      "activity" : "generate1",
      "start" : 88,
      "length" : 133
    },
    {
      "activity" : "generate2",
      "start" : 99,
      "length" : 285
    },
    {
      "activity" : "generate2",
      "start" : 108,
      "length" : 105
    },
    {
      "activity" : "generateValidationPack",
      "start" : 126,
      "length" : 5
    }]
  },
  {
    "name" : "fsh-generated/resources/StructureDefinition-ror-organisation-interne.json",
    "size" : 3051,
    "processes" : [{
      "activity" : "loadResources",
      "start" : 57,
      "length" : 2
    },
    {
      "activity" : "load",
      "start" : 58,
      "length" : 5
    },
    {
      "activity" : "generateSnapshots",
      "start" : 58,
      "length" : 12
    },
    {
      "activity" : "generateNarratives",
      "start" : 62,
      "length" : 12
    },
    {
      "activity" : "validate",
      "start" : 80,
      "length" : 46
    },
    {
      "activity" : "validate",
      "start" : 86,
      "length" : 1
    },
    {
      "activity" : "generate1",
      "start" : 88,
      "length" : 67
    },
    {
      "activity" : "generate2",
      "start" : 99,
      "length" : 158
    },
    {
      "activity" : "generate2",
      "start" : 108,
      "length" : 49
    },
    {
      "activity" : "generateValidationPack",
      "start" : 126,
      "length" : 1
    }]
  },
  {
    "name" : "fsh-generated/resources/StructureDefinition-ror-orientation-particuliere.json",
    "size" : 1558,
    "processes" : [{
      "activity" : "loadResources",
      "start" : 57,
      "length" : 1
    },
    {
      "activity" : "load",
      "start" : 58,
      "length" : 4
    },
    {
      "activity" : "generateSnapshots",
      "start" : 58,
      "length" : 11
    },
    {
      "activity" : "generateNarratives",
      "start" : 62,
      "length" : 8
    },
    {
      "activity" : "validate",
      "start" : 80,
      "length" : 37
    },
    {
      "activity" : "generate1",
      "start" : 88,
      "length" : 31
    },
    {
      "activity" : "generate2",
      "start" : 100,
      "length" : 124
    },
    {
      "activity" : "generate2",
      "start" : 108,
      "length" : 29
    },
    {
      "activity" : "generateValidationPack",
      "start" : 126,
      "length" : 1
    }]
  },
  {
    "name" : "fsh-generated/resources/StructureDefinition-ror-patientele.json",
    "size" : 2424,
    "processes" : [{
      "activity" : "loadResources",
      "start" : 57,
      "length" : 2
    },
    {
      "activity" : "load",
      "start" : 58,
      "length" : 4
    },
    {
      "activity" : "generateSnapshots",
      "start" : 58,
      "length" : 10
    },
    {
      "activity" : "generateNarratives",
      "start" : 62,
      "length" : 9
    },
    {
      "activity" : "validate",
      "start" : 80,
      "length" : 535
    },
    {
      "activity" : "validate",
      "start" : 84,
      "length" : 1
    },
    {
      "activity" : "checkConformanceResources3",
      "start" : 86,
      "length" : 1
    },
    {
      "activity" : "generate1",
      "start" : 88,
      "length" : 38
    },
    {
      "activity" : "generate2",
      "start" : 100,
      "length" : 132
    },
    {
      "activity" : "generate2",
      "start" : 108,
      "length" : 69
    },
    {
      "activity" : "generateValidationPack",
      "start" : 126,
      "length" : 2
    }]
  },
  {
    "name" : "fsh-generated/resources/StructureDefinition-ror-personne-physique.json",
    "size" : 2008,
    "processes" : [{
      "activity" : "loadResources",
      "start" : 57,
      "length" : 1
    },
    {
      "activity" : "load",
      "start" : 58,
      "length" : 3
    },
    {
      "activity" : "generateSnapshots",
      "start" : 58,
      "length" : 21
    },
    {
      "activity" : "load-configure",
      "start" : 59,
      "length" : 1
    },
    {
      "activity" : "generateNarratives",
      "start" : 62,
      "length" : 18
    },
    {
      "activity" : "validate",
      "start" : 81,
      "length" : 2117
    },
    {
      "activity" : "checkConformanceResources",
      "start" : 86,
      "length" : 1
    },
    {
      "activity" : "validate",
      "start" : 86,
      "length" : 1
    },
    {
      "activity" : "generate1",
      "start" : 88,
      "length" : 75
    },
    {
      "activity" : "generate2",
      "start" : 100,
      "length" : 269
    },
    {
      "activity" : "generate2",
      "start" : 108,
      "length" : 90
    },
    {
      "activity" : "generateValidationPack",
      "start" : 126,
      "length" : 3
    }]
  },
  {
    "name" : "fsh-generated/resources/StructureDefinition-ror-pole.json",
    "size" : 1157,
    "processes" : [{
      "activity" : "loadResources",
      "start" : 57,
      "length" : 1
    },
    {
      "activity" : "load",
      "start" : 58,
      "length" : 3
    },
    {
      "activity" : "generateSnapshots",
      "start" : 58,
      "length" : 4
    },
    {
      "activity" : "generateNarratives",
      "start" : 62,
      "length" : 9
    },
    {
      "activity" : "validate",
      "start" : 83,
      "length" : 7
    },
    {
      "activity" : "generate1",
      "start" : 88,
      "length" : 23
    },
    {
      "activity" : "generate2",
      "start" : 100,
      "length" : 98
    },
    {
      "activity" : "generate2",
      "start" : 108,
      "length" : 16
    },
    {
      "activity" : "generateValidationPack",
      "start" : 126,
      "length" : 1
    }]
  },
  {
    "name" : "fsh-generated/resources/StructureDefinition-ror-professionnel.json",
    "size" : 1901,
    "processes" : [{
      "activity" : "loadResources",
      "start" : 57,
      "length" : 1
    },
    {
      "activity" : "load",
      "start" : 58,
      "length" : 3
    },
    {
      "activity" : "generateSnapshots",
      "start" : 58,
      "length" : 9
    },
    {
      "activity" : "generateNarratives",
      "start" : 62,
      "length" : 10
    },
    {
      "activity" : "validate",
      "start" : 83,
      "length" : 553
    },
    {
      "activity" : "generate1",
      "start" : 88,
      "length" : 51
    },
    {
      "activity" : "generate2",
      "start" : 100,
      "length" : 167
    },
    {
      "activity" : "generate2",
      "start" : 108,
      "length" : 50
    },
    {
      "activity" : "generateValidationPack",
      "start" : 126,
      "length" : 2
    },
    {
      "activity" : "scanExamplesForR5",
      "start" : 140,
      "length" : 1
    }]
  },
  {
    "name" : "fsh-generated/resources/StructureDefinition-ror-qualification-pac.json",
    "size" : 1508,
    "processes" : [{
      "activity" : "loadResources",
      "start" : 57,
      "length" : 1
    },
    {
      "activity" : "load",
      "start" : 58,
      "length" : 2
    },
    {
      "activity" : "generateSnapshots",
      "start" : 59,
      "length" : 8
    },
    {
      "activity" : "generateNarratives",
      "start" : 62,
      "length" : 9
    },
    {
      "activity" : "validate",
      "start" : 83,
      "length" : 24
    },
    {
      "activity" : "checkConformanceResources3",
      "start" : 86,
      "length" : 1
    },
    {
      "activity" : "validate",
      "start" : 86,
      "length" : 1
    },
    {
      "activity" : "generate1",
      "start" : 88,
      "length" : 41
    },
    {
      "activity" : "generate2",
      "start" : 100,
      "length" : 123
    },
    {
      "activity" : "generate2",
      "start" : 108,
      "length" : 25
    },
    {
      "activity" : "generateValidationPack",
      "start" : 126,
      "length" : 1
    }]
  },
  {
    "name" : "fsh-generated/resources/StructureDefinition-ror-savoir-faire.json",
    "size" : 2056,
    "processes" : [{
      "activity" : "loadResources",
      "start" : 57,
      "length" : 2
    },
    {
      "activity" : "load",
      "start" : 58,
      "length" : 3
    },
    {
      "activity" : "generateSnapshots",
      "start" : 59,
      "length" : 7
    },
    {
      "activity" : "generateNarratives",
      "start" : 62,
      "length" : 8
    },
    {
      "activity" : "validate",
      "start" : 83,
      "length" : 19
    },
    {
      "activity" : "checkConformanceResources",
      "start" : 86,
      "length" : 1
    },
    {
      "activity" : "generate1",
      "start" : 88,
      "length" : 35
    },
    {
      "activity" : "generate2",
      "start" : 101,
      "length" : 118
    },
    {
      "activity" : "generate2",
      "start" : 108,
      "length" : 25
    },
    {
      "activity" : "generateValidationPack",
      "start" : 126,
      "length" : 1
    }]
  },
  {
    "name" : "fsh-generated/resources/StructureDefinition-ror-situation-operationnelle.json",
    "size" : 2945,
    "processes" : [{
      "activity" : "loadResources",
      "start" : 57,
      "length" : 2
    },
    {
      "activity" : "load",
      "start" : 58,
      "length" : 3
    },
    {
      "activity" : "generateSnapshots",
      "start" : 59,
      "length" : 7
    },
    {
      "activity" : "generateNarratives",
      "start" : 62,
      "length" : 13
    },
    {
      "activity" : "validate",
      "start" : 83,
      "length" : 38
    },
    {
      "activity" : "validate",
      "start" : 86,
      "length" : 1
    },
    {
      "activity" : "generate1",
      "start" : 88,
      "length" : 51
    },
    {
      "activity" : "generate2",
      "start" : 101,
      "length" : 152
    },
    {
      "activity" : "generate2",
      "start" : 108,
      "length" : 39
    },
    {
      "activity" : "makeDependencies",
      "start" : 109,
      "length" : 1
    },
    {
      "activity" : "generateValidationPack",
      "start" : 126,
      "length" : 2
    }]
  },
  {
    "name" : "fsh-generated/resources/StructureDefinition-ror-specialite.json",
    "size" : 1393,
    "processes" : [{
      "activity" : "loadResources",
      "start" : 57,
      "length" : 2
    },
    {
      "activity" : "load",
      "start" : 58,
      "length" : 3
    },
    {
      "activity" : "generateSnapshots",
      "start" : 59,
      "length" : 8
    },
    {
      "activity" : "checkR4R4B",
      "start" : 59,
      "length" : 1
    },
    {
      "activity" : "generateNarratives",
      "start" : 62,
      "length" : 9
    },
    {
      "activity" : "validate",
      "start" : 83,
      "length" : 41
    },
    {
      "activity" : "generate1",
      "start" : 88,
      "length" : 30
    },
    {
      "activity" : "generate2",
      "start" : 101,
      "length" : 127
    },
    {
      "activity" : "generate2",
      "start" : 108,
      "length" : 22
    }]
  },
  {
    "name" : "fsh-generated/resources/StructureDefinition-ror-structure-interne.json",
    "size" : 1272,
    "processes" : [{
      "activity" : "loadResources",
      "start" : 57,
      "length" : 2
    },
    {
      "activity" : "load",
      "start" : 58,
      "length" : 2
    },
    {
      "activity" : "generateSnapshots",
      "start" : 59,
      "length" : 4
    },
    {
      "activity" : "generateNarratives",
      "start" : 62,
      "length" : 6
    },
    {
      "activity" : "validate",
      "start" : 83,
      "length" : 10
    },
    {
      "activity" : "checkConformanceResources3",
      "start" : 86,
      "length" : 1
    },
    {
      "activity" : "generate1",
      "start" : 88,
      "length" : 19
    },
    {
      "activity" : "generate2",
      "start" : 101,
      "length" : 98
    },
    {
      "activity" : "generate2",
      "start" : 108,
      "length" : 16
    },
    {
      "activity" : "generateValidationPack",
      "start" : 126,
      "length" : 1
    }]
  },
  {
    "name" : "fsh-generated/resources/StructureDefinition-ror-supplement-tarif-hebergement.json",
    "size" : 2140,
    "processes" : [{
      "activity" : "loadResources",
      "start" : 57,
      "length" : 1
    },
    {
      "activity" : "load",
      "start" : 58,
      "length" : 3
    },
    {
      "activity" : "generateSnapshots",
      "start" : 59,
      "length" : 5
    },
    {
      "activity" : "generateNarratives",
      "start" : 62,
      "length" : 8
    },
    {
      "activity" : "validate",
      "start" : 84,
      "length" : 20
    },
    {
      "activity" : "validate",
      "start" : 86,
      "length" : 1
    },
    {
      "activity" : "generate1",
      "start" : 88,
      "length" : 30
    },
    {
      "activity" : "generate2",
      "start" : 101,
      "length" : 96
    },
    {
      "activity" : "generate2",
      "start" : 108,
      "length" : 36
    },
    {
      "activity" : "generateValidationPack",
      "start" : 126,
      "length" : 1
    }]
  },
  {
    "name" : "fsh-generated/resources/StructureDefinition-ror-surspecialite-transversale.json",
    "size" : 1672,
    "processes" : [{
      "activity" : "loadResources",
      "start" : 57,
      "length" : 2
    },
    {
      "activity" : "load",
      "start" : 58,
      "length" : 2
    },
    {
      "activity" : "generateSnapshots",
      "start" : 59,
      "length" : 7
    },
    {
      "activity" : "generateNarratives",
      "start" : 62,
      "length" : 8
    },
    {
      "activity" : "validate",
      "start" : 84,
      "length" : 27
    },
    {
      "activity" : "checkConformanceResources",
      "start" : 86,
      "length" : 1
    },
    {
      "activity" : "generate1",
      "start" : 88,
      "length" : 34
    },
    {
      "activity" : "generate2",
      "start" : 101,
      "length" : 96
    },
    {
      "activity" : "generate2",
      "start" : 108,
      "length" : 29
    },
    {
      "activity" : "generateValidationPack",
      "start" : 126,
      "length" : 1
    }]
  },
  {
    "name" : "fsh-generated/resources/StructureDefinition-ror-tarif-accueil-de-jour.json",
    "size" : 2062,
    "processes" : [{
      "activity" : "loadResources",
      "start" : 57,
      "length" : 2
    },
    {
      "activity" : "load",
      "start" : 58,
      "length" : 3
    },
    {
      "activity" : "generateSnapshots",
      "start" : 59,
      "length" : 6
    },
    {
      "activity" : "load-configure",
      "start" : 59,
      "length" : 1
    },
    {
      "activity" : "generateNarratives",
      "start" : 62,
      "length" : 74
    },
    {
      "activity" : "validate",
      "start" : 84,
      "length" : 21
    },
    {
      "activity" : "scanForUsageStats",
      "start" : 86,
      "length" : 1
    },
    {
      "activity" : "validate",
      "start" : 86,
      "length" : 1
    },
    {
      "activity" : "generate1",
      "start" : 88,
      "length" : 33
    },
    {
      "activity" : "generate2",
      "start" : 101,
      "length" : 92
    },
    {
      "activity" : "generate2",
      "start" : 108,
      "length" : 25
    },
    {
      "activity" : "generateValidationPack",
      "start" : 126,
      "length" : 1
    }]
  },
  {
    "name" : "fsh-generated/resources/StructureDefinition-ror-tarif-aides-humaines.json",
    "size" : 3167,
    "processes" : [{
      "activity" : "loadResources",
      "start" : 57,
      "length" : 2
    },
    {
      "activity" : "load",
      "start" : 58,
      "length" : 3
    },
    {
      "activity" : "generateSnapshots",
      "start" : 59,
      "length" : 7
    },
    {
      "activity" : "generateNarratives",
      "start" : 62,
      "length" : 12
    },
    {
      "activity" : "validate",
      "start" : 84,
      "length" : 29
    },
    {
      "activity" : "checkConformanceResources3",
      "start" : 86,
      "length" : 1
    },
    {
      "activity" : "validate",
      "start" : 86,
      "length" : 1
    },
    {
      "activity" : "generate1",
      "start" : 88,
      "length" : 37
    },
    {
      "activity" : "generate2",
      "start" : 101,
      "length" : 99
    },
    {
      "activity" : "generate2",
      "start" : 108,
      "length" : 26
    },
    {
      "activity" : "generateValidationPack",
      "start" : 126,
      "length" : 1
    }]
  },
  {
    "name" : "fsh-generated/resources/StructureDefinition-ror-tarif-dependance.json",
    "size" : 2717,
    "processes" : [{
      "activity" : "loadResources",
      "start" : 57,
      "length" : 1
    },
    {
      "activity" : "load",
      "start" : 58,
      "length" : 4
    },
    {
      "activity" : "generateSnapshots",
      "start" : 59,
      "length" : 7
    },
    {
      "activity" : "generateNarratives",
      "start" : 62,
      "length" : 13
    },
    {
      "activity" : "validate",
      "start" : 84,
      "length" : 25
    },
    {
      "activity" : "generate1",
      "start" : 88,
      "length" : 36
    },
    {
      "activity" : "generate2",
      "start" : 101,
      "length" : 102
    },
    {
      "activity" : "generate2",
      "start" : 108,
      "length" : 27
    },
    {
      "activity" : "generateValidationPack",
      "start" : 126,
      "length" : 1
    }]
  },
  {
    "name" : "fsh-generated/resources/StructureDefinition-ror-tarif-portage-repas.json",
    "size" : 2503,
    "processes" : [{
      "activity" : "loadResources",
      "start" : 57,
      "length" : 2
    },
    {
      "activity" : "load",
      "start" : 58,
      "length" : 5
    },
    {
      "activity" : "generateSnapshots",
      "start" : 59,
      "length" : 7
    },
    {
      "activity" : "generateNarratives",
      "start" : 62,
      "length" : 9
    },
    {
      "activity" : "validate",
      "start" : 84,
      "length" : 30
    },
    {
      "activity" : "validate",
      "start" : 86,
      "length" : 1
    },
    {
      "activity" : "generate1",
      "start" : 88,
      "length" : 33
    },
    {
      "activity" : "generate2",
      "start" : 101,
      "length" : 91
    },
    {
      "activity" : "generate2",
      "start" : 108,
      "length" : 25
    },
    {
      "activity" : "generateValidationPack",
      "start" : 126,
      "length" : 1
    }]
  },
  {
    "name" : "fsh-generated/resources/StructureDefinition-ror-tarif-prestation-supplementaire.json",
    "size" : 2716,
    "processes" : [{
      "activity" : "loadResources",
      "start" : 57,
      "length" : 1
    },
    {
      "activity" : "load",
      "start" : 58,
      "length" : 5
    },
    {
      "activity" : "generateSnapshots",
      "start" : 59,
      "length" : 8
    },
    {
      "activity" : "generateNarratives",
      "start" : 62,
      "length" : 10
    },
    {
      "activity" : "validate",
      "start" : 84,
      "length" : 18
    },
    {
      "activity" : "generate1",
      "start" : 88,
      "length" : 35
    },
    {
      "activity" : "generate2",
      "start" : 102,
      "length" : 118
    },
    {
      "activity" : "generate2",
      "start" : 108,
      "length" : 25
    },
    {
      "activity" : "generateValidationPack",
      "start" : 126,
      "length" : 1
    }]
  },
  {
    "name" : "fsh-generated/resources/StructureDefinition-ror-tarif.json",
    "size" : 3936,
    "processes" : [{
      "activity" : "loadResources",
      "start" : 57,
      "length" : 1
    },
    {
      "activity" : "load",
      "start" : 58,
      "length" : 6
    },
    {
      "activity" : "generateNarratives",
      "start" : 62,
      "length" : 10
    },
    {
      "activity" : "validate",
      "start" : 84,
      "length" : 19
    },
    {
      "activity" : "checkConformanceResources",
      "start" : 86,
      "length" : 1
    },
    {
      "activity" : "checkConformanceResources3",
      "start" : 86,
      "length" : 1
    },
    {
      "activity" : "validate",
      "start" : 86,
      "length" : 1
    },
    {
      "activity" : "generate1",
      "start" : 88,
      "length" : 37
    },
    {
      "activity" : "generate2",
      "start" : 102,
      "length" : 100
    },
    {
      "activity" : "generate2",
      "start" : 108,
      "length" : 24
    },
    {
      "activity" : "generateValidationPack",
      "start" : 126,
      "length" : 1
    }]
  },
  {
    "name" : "fsh-generated/resources/StructureDefinition-ror-unite-fonctionnelle.json",
    "size" : 1329,
    "processes" : [{
      "activity" : "loadResources",
      "start" : 57,
      "length" : 1
    },
    {
      "activity" : "load",
      "start" : 58,
      "length" : 4
    },
    {
      "activity" : "generateSnapshots",
      "start" : 59,
      "length" : 5
    },
    {
      "activity" : "generateNarratives",
      "start" : 62,
      "length" : 6
    },
    {
      "activity" : "validate",
      "start" : 84,
      "length" : 6
    },
    {
      "activity" : "generate1",
      "start" : 88,
      "length" : 19
    },
    {
      "activity" : "generate2",
      "start" : 102,
      "length" : 106
    },
    {
      "activity" : "generate2",
      "start" : 108,
      "length" : 14
    },
    {
      "activity" : "generateValidationPack",
      "start" : 126,
      "length" : 1
    },
    {
      "activity" : "scanProfilesForR5",
      "start" : 140,
      "length" : 1
    }]
  },
  {
    "name" : "fsh-generated/resources/ValueSet-jdv-ror-accessibilite-lieu.json",
    "size" : 633,
    "processes" : [{
      "activity" : "loadResources",
      "start" : 57,
      "length" : 1
    },
    {
      "activity" : "load",
      "start" : 57,
      "length" : 10
    },
    {
      "activity" : "generateNarratives",
      "start" : 62,
      "length" : 145
    },
    {
      "activity" : "validate",
      "start" : 63,
      "length" : 1479
    },
    {
      "activity" : "validate",
      "start" : 86,
      "length" : 1
    },
    {
      "activity" : "generate1",
      "start" : 88,
      "length" : 14
    },
    {
      "activity" : "generate2",
      "start" : 102,
      "length" : 119
    },
    {
      "activity" : "generateValidationPack",
      "start" : 126,
      "length" : 1
    }]
  },
  {
    "name" : "fsh-generated/resources/ValueSet-jdv-ror-acte-specifique.json",
    "size" : 612,
    "processes" : [{
      "activity" : "loadResources",
      "start" : 57,
      "length" : 1
    },
    {
      "activity" : "load",
      "start" : 57,
      "length" : 147
    },
    {
      "activity" : "generateNarratives",
      "start" : 62,
      "length" : 3
    },
    {
      "activity" : "validate",
      "start" : 65,
      "length" : 15
    },
    {
      "activity" : "generate1",
      "start" : 88,
      "length" : 10
    },
    {
      "activity" : "generate2",
      "start" : 102,
      "length" : 427
    },
    {
      "activity" : "generateValidationPack",
      "start" : 126,
      "length" : 20
    }]
  },
  {
    "name" : "fsh-generated/resources/ValueSet-jdv-ror-activite-operationnelle.json",
    "size" : 669,
    "processes" : [{
      "activity" : "loadResources",
      "start" : 57,
      "length" : 1
    },
    {
      "activity" : "load",
      "start" : 58,
      "length" : 31
    },
    {
      "activity" : "generateNarratives",
      "start" : 62,
      "length" : 3
    },
    {
      "activity" : "validate",
      "start" : 65,
      "length" : 10
    },
    {
      "activity" : "checkConformanceResources3",
      "start" : 86,
      "length" : 1
    },
    {
      "activity" : "validate",
      "start" : 86,
      "length" : 1
    },
    {
      "activity" : "generate1",
      "start" : 88,
      "length" : 10
    },
    {
      "activity" : "generate2",
      "start" : 102,
      "length" : 172
    },
    {
      "activity" : "generateValidationPack",
      "start" : 126,
      "length" : 7
    },
    {
      "activity" : "scanExamplesForR5",
      "start" : 140,
      "length" : 1
    }]
  },
  {
    "name" : "fsh-generated/resources/ValueSet-jdv-ror-affectation-temporaire.json",
    "size" : 660,
    "processes" : [{
      "activity" : "loadResources",
      "start" : 57,
      "length" : 1
    },
    {
      "activity" : "load",
      "start" : 58,
      "length" : 5
    },
    {
      "activity" : "checkR4R4B",
      "start" : 59,
      "length" : 1
    },
    {
      "activity" : "generateNarratives",
      "start" : 62,
      "length" : 2
    },
    {
      "activity" : "validate",
      "start" : 65,
      "length" : 14
    },
    {
      "activity" : "generate1",
      "start" : 88,
      "length" : 12
    },
    {
      "activity" : "generate2",
      "start" : 103,
      "length" : 62
    },
    {
      "activity" : "generateValidationPack",
      "start" : 126,
      "length" : 1
    }]
  },
  {
    "name" : "fsh-generated/resources/ValueSet-jdv-ror-agreg-statut-juridique-niv2.json",
    "size" : 713,
    "processes" : [{
      "activity" : "loadResources",
      "start" : 57,
      "length" : 1
    },
    {
      "activity" : "load",
      "start" : 58,
      "length" : 5
    },
    {
      "activity" : "generateNarratives",
      "start" : 62,
      "length" : 3
    },
    {
      "activity" : "validate",
      "start" : 65,
      "length" : 18
    },
    {
      "activity" : "validate",
      "start" : 86,
      "length" : 1
    },
    {
      "activity" : "generate1",
      "start" : 88,
      "length" : 14
    },
    {
      "activity" : "generate2",
      "start" : 103,
      "length" : 57
    }]
  },
  {
    "name" : "fsh-generated/resources/ValueSet-jdv-ror-aide-financiere.json",
    "size" : 612,
    "processes" : [{
      "activity" : "load",
      "start" : 58,
      "length" : 6
    },
    {
      "activity" : "generateNarratives",
      "start" : 62,
      "length" : 2
    },
    {
      "activity" : "validate",
      "start" : 65,
      "length" : 13
    },
    {
      "activity" : "generate1",
      "start" : 88,
      "length" : 14
    },
    {
      "activity" : "generate2",
      "start" : 103,
      "length" : 55
    }]
  },
  {
    "name" : "fsh-generated/resources/ValueSet-jdv-ror-capacite-savoir-faire.json",
    "size" : 650,
    "processes" : [{
      "activity" : "loadResources",
      "start" : 57,
      "length" : 1
    },
    {
      "activity" : "load",
      "start" : 58,
      "length" : 7
    },
    {
      "activity" : "generateNarratives",
      "start" : 62,
      "length" : 2
    },
    {
      "activity" : "validate",
      "start" : 65,
      "length" : 10
    },
    {
      "activity" : "checkConformanceResources3",
      "start" : 86,
      "length" : 1
    },
    {
      "activity" : "validate",
      "start" : 86,
      "length" : 1
    },
    {
      "activity" : "generate1",
      "start" : 88,
      "length" : 14
    },
    {
      "activity" : "generate2",
      "start" : 103,
      "length" : 55
    },
    {
      "activity" : "generateValidationPack",
      "start" : 126,
      "length" : 1
    }]
  },
  {
    "name" : "fsh-generated/resources/ValueSet-jdv-ror-champ-activite.json",
    "size" : 607,
    "processes" : [{
      "activity" : "loadResources",
      "start" : 57,
      "length" : 1
    },
    {
      "activity" : "load",
      "start" : 58,
      "length" : 5
    },
    {
      "activity" : "generateNarratives",
      "start" : 62,
      "length" : 3
    },
    {
      "activity" : "validate",
      "start" : 65,
      "length" : 9
    },
    {
      "activity" : "validate",
      "start" : 86,
      "length" : 1
    },
    {
      "activity" : "generate1",
      "start" : 89,
      "length" : 10
    },
    {
      "activity" : "generate2",
      "start" : 103,
      "length" : 52
    }]
  },
  {
    "name" : "fsh-generated/resources/ValueSet-jdv-ror-civilite-exercice.json",
    "size" : 625,
    "processes" : [{
      "activity" : "load",
      "start" : 58,
      "length" : 4
    },
    {
      "activity" : "checkR4R4B",
      "start" : 59,
      "length" : 1
    },
    {
      "activity" : "generateNarratives",
      "start" : 62,
      "length" : 2
    },
    {
      "activity" : "validate",
      "start" : 65,
      "length" : 9
    },
    {
      "activity" : "generate1",
      "start" : 89,
      "length" : 11
    },
    {
      "activity" : "generate2",
      "start" : 103,
      "length" : 48
    },
    {
      "activity" : "generateValidationPack",
      "start" : 126,
      "length" : 1
    }]
  },
  {
    "name" : "fsh-generated/resources/ValueSet-jdv-ror-civilite.json",
    "size" : 564,
    "processes" : [{
      "activity" : "loadResources",
      "start" : 57,
      "length" : 1
    },
    {
      "activity" : "load",
      "start" : 58,
      "length" : 5
    },
    {
      "activity" : "generateNarratives",
      "start" : 62,
      "length" : 2
    },
    {
      "activity" : "validate",
      "start" : 65,
      "length" : 10
    },
    {
      "activity" : "validate",
      "start" : 86,
      "length" : 1
    },
    {
      "activity" : "generate1",
      "start" : 89,
      "length" : 13
    },
    {
      "activity" : "generate2",
      "start" : 103,
      "length" : 45
    }]
  },
  {
    "name" : "fsh-generated/resources/ValueSet-jdv-ror-competence-exclusive.json",
    "size" : 644,
    "processes" : [{
      "activity" : "load",
      "start" : 58,
      "length" : 5
    },
    {
      "activity" : "generateNarratives",
      "start" : 62,
      "length" : 2
    },
    {
      "activity" : "validate",
      "start" : 65,
      "length" : 9
    },
    {
      "activity" : "checkConformanceResources3",
      "start" : 86,
      "length" : 1
    },
    {
      "activity" : "generate1",
      "start" : 89,
      "length" : 12
    },
    {
      "activity" : "generate2",
      "start" : 103,
      "length" : 49
    }]
  },
  {
    "name" : "fsh-generated/resources/ValueSet-jdv-ror-competence-specifique.json",
    "size" : 655,
    "processes" : [{
      "activity" : "loadResources",
      "start" : 57,
      "length" : 1
    },
    {
      "activity" : "load",
      "start" : 58,
      "length" : 9
    },
    {
      "activity" : "generateNarratives",
      "start" : 62,
      "length" : 3
    },
    {
      "activity" : "validate",
      "start" : 65,
      "length" : 9
    },
    {
      "activity" : "validate",
      "start" : 86,
      "length" : 1
    },
    {
      "activity" : "generate1",
      "start" : 89,
      "length" : 13
    },
    {
      "activity" : "generate2",
      "start" : 103,
      "length" : 53
    },
    {
      "activity" : "generateValidationPack",
      "start" : 126,
      "length" : 1
    }]
  },
  {
    "name" : "fsh-generated/resources/ValueSet-jdv-ror-competence.json",
    "size" : 578,
    "processes" : [{
      "activity" : "load",
      "start" : 58,
      "length" : 7
    },
    {
      "activity" : "checkR4R4B",
      "start" : 59,
      "length" : 1
    },
    {
      "activity" : "generateNarratives",
      "start" : 62,
      "length" : 2
    },
    {
      "activity" : "validate",
      "start" : 65,
      "length" : 9
    },
    {
      "activity" : "generate1",
      "start" : 89,
      "length" : 9
    },
    {
      "activity" : "generate2",
      "start" : 103,
      "length" : 56
    },
    {
      "activity" : "generateValidationPack",
      "start" : 126,
      "length" : 1
    }]
  },
  {
    "name" : "fsh-generated/resources/ValueSet-jdv-ror-condition-tarifaire.json",
    "size" : 639,
    "processes" : [{
      "activity" : "loadResources",
      "start" : 57,
      "length" : 1
    },
    {
      "activity" : "load",
      "start" : 58,
      "length" : 4
    },
    {
      "activity" : "generateNarratives",
      "start" : 62,
      "length" : 2
    },
    {
      "activity" : "validate",
      "start" : 65,
      "length" : 9
    },
    {
      "activity" : "validate",
      "start" : 86,
      "length" : 1
    },
    {
      "activity" : "generate1",
      "start" : 89,
      "length" : 9
    },
    {
      "activity" : "generate2",
      "start" : 103,
      "length" : 44
    }]
  },
  {
    "name" : "fsh-generated/resources/ValueSet-jdv-ror-desc-non-qualifiant.json",
    "size" : 632,
    "processes" : [{
      "activity" : "loadResources",
      "start" : 57,
      "length" : 1
    },
    {
      "activity" : "load",
      "start" : 58,
      "length" : 7
    },
    {
      "activity" : "load-configure",
      "start" : 59,
      "length" : 1
    },
    {
      "activity" : "generateNarratives",
      "start" : 62,
      "length" : 2
    },
    {
      "activity" : "validate",
      "start" : 65,
      "length" : 9
    },
    {
      "activity" : "generate1",
      "start" : 89,
      "length" : 11
    },
    {
      "activity" : "generate2",
      "start" : 103,
      "length" : 44
    },
    {
      "activity" : "generateValidationPack",
      "start" : 126,
      "length" : 1
    }]
  },
  {
    "name" : "fsh-generated/resources/ValueSet-jdv-ror-droit-exercice-complementaire.json",
    "size" : 678,
    "processes" : [{
      "activity" : "loadResources",
      "start" : 57,
      "length" : 1
    },
    {
      "activity" : "load",
      "start" : 58,
      "length" : 7
    },
    {
      "activity" : "generateNarratives",
      "start" : 62,
      "length" : 2
    },
    {
      "activity" : "validate",
      "start" : 65,
      "length" : 8
    },
    {
      "activity" : "checkConformanceResources3",
      "start" : 86,
      "length" : 1
    },
    {
      "activity" : "validate",
      "start" : 86,
      "length" : 1
    },
    {
      "activity" : "generate1",
      "start" : 89,
      "length" : 12
    },
    {
      "activity" : "generate2",
      "start" : 103,
      "length" : 43
    },
    {
      "activity" : "generateValidationPack",
      "start" : 126,
      "length" : 1
    }]
  },
  {
    "name" : "fsh-generated/resources/ValueSet-jdv-ror-equipement.json",
    "size" : 581,
    "processes" : [{
      "activity" : "loadResources",
      "start" : 57,
      "length" : 1
    },
    {
      "activity" : "load",
      "start" : 58,
      "length" : 15
    },
    {
      "activity" : "checkR4R4B",
      "start" : 59,
      "length" : 1
    },
    {
      "activity" : "generateNarratives",
      "start" : 62,
      "length" : 2
    },
    {
      "activity" : "validate",
      "start" : 65,
      "length" : 8
    },
    {
      "activity" : "generate1",
      "start" : 89,
      "length" : 9
    },
    {
      "activity" : "generate2",
      "start" : 103,
      "length" : 74
    },
    {
      "activity" : "generateValidationPack",
      "start" : 126,
      "length" : 3
    }]
  },
  {
    "name" : "fsh-generated/resources/ValueSet-jdv-ror-espic.json",
    "size" : 591,
    "processes" : [{
      "activity" : "load",
      "start" : 58,
      "length" : 5
    },
    {
      "activity" : "generateNarratives",
      "start" : 62,
      "length" : 2
    },
    {
      "activity" : "validate",
      "start" : 65,
      "length" : 10
    },
    {
      "activity" : "validate",
      "start" : 86,
      "length" : 1
    },
    {
      "activity" : "generate1",
      "start" : 89,
      "length" : 10
    },
    {
      "activity" : "generate2",
      "start" : 103,
      "length" : 38
    },
    {
      "activity" : "generateValidationPack",
      "start" : 126,
      "length" : 1
    }]
  },
  {
    "name" : "fsh-generated/resources/ValueSet-jdv-ror-finess-statut-juridique.json",
    "size" : 660,
    "processes" : [{
      "activity" : "loadResources",
      "start" : 57,
      "length" : 1
    },
    {
      "activity" : "load",
      "start" : 58,
      "length" : 7
    },
    {
      "activity" : "generateNarratives",
      "start" : 62,
      "length" : 2
    },
    {
      "activity" : "validate",
      "start" : 65,
      "length" : 9
    },
    {
      "activity" : "generate1",
      "start" : 89,
      "length" : 12
    },
    {
      "activity" : "generate2",
      "start" : 103,
      "length" : 52
    },
    {
      "activity" : "generateValidationPack",
      "start" : 126,
      "length" : 1
    }]
  },
  {
    "name" : "fsh-generated/resources/ValueSet-jdv-ror-genre-capacite.json",
    "size" : 608,
    "processes" : [{
      "activity" : "load",
      "start" : 58,
      "length" : 4
    },
    {
      "activity" : "checkR4R4B",
      "start" : 59,
      "length" : 1
    },
    {
      "activity" : "generateNarratives",
      "start" : 62,
      "length" : 2
    },
    {
      "activity" : "validate",
      "start" : 65,
      "length" : 7
    },
    {
      "activity" : "checkConformanceResources3",
      "start" : 86,
      "length" : 1
    },
    {
      "activity" : "validate",
      "start" : 86,
      "length" : 1
    },
    {
      "activity" : "generate1",
      "start" : 89,
      "length" : 11
    },
    {
      "activity" : "generate2",
      "start" : 103,
      "length" : 41
    }]
  },
  {
    "name" : "fsh-generated/resources/ValueSet-jdv-ror-modalite-accueil.json",
    "size" : 621,
    "processes" : [{
      "activity" : "loadResources",
      "start" : 57,
      "length" : 1
    },
    {
      "activity" : "load",
      "start" : 58,
      "length" : 5
    },
    {
      "activity" : "generateNarratives",
      "start" : 62,
      "length" : 2
    },
    {
      "activity" : "validate",
      "start" : 65,
      "length" : 7
    },
    {
      "activity" : "generate1",
      "start" : 89,
      "length" : 10
    },
    {
      "activity" : "generate2",
      "start" : 103,
      "length" : 41
    },
    {
      "activity" : "generateValidationPack",
      "start" : 126,
      "length" : 1
    }]
  },
  {
    "name" : "fsh-generated/resources/ValueSet-jdv-ror-mode-exercice.json",
    "size" : 596,
    "processes" : [{
      "activity" : "load",
      "start" : 58,
      "length" : 4
    },
    {
      "activity" : "generateNarratives",
      "start" : 62,
      "length" : 3
    },
    {
      "activity" : "validate",
      "start" : 65,
      "length" : 7
    },
    {
      "activity" : "validate",
      "start" : 86,
      "length" : 1
    },
    {
      "activity" : "generate1",
      "start" : 89,
      "length" : 9
    },
    {
      "activity" : "generate2",
      "start" : 104,
      "length" : 39
    }]
  },
  {
    "name" : "fsh-generated/resources/ValueSet-jdv-ror-mode-gestion.json",
    "size" : 593,
    "processes" : [{
      "activity" : "loadResources",
      "start" : 57,
      "length" : 1
    },
    {
      "activity" : "load",
      "start" : 58,
      "length" : 4
    },
    {
      "activity" : "generateNarratives",
      "start" : 62,
      "length" : 2
    },
    {
      "activity" : "validate",
      "start" : 65,
      "length" : 6
    },
    {
      "activity" : "generate1",
      "start" : 89,
      "length" : 12
    },
    {
      "activity" : "generate2",
      "start" : 104,
      "length" : 38
    }]
  },
  {
    "name" : "fsh-generated/resources/ValueSet-jdv-ror-mode-prise-en-charge.json",
    "size" : 641,
    "processes" : [{
      "activity" : "loadResources",
      "start" : 57,
      "length" : 1
    },
    {
      "activity" : "load",
      "start" : 58,
      "length" : 7
    },
    {
      "activity" : "checkR4R4B",
      "start" : 59,
      "length" : 1
    },
    {
      "activity" : "generateNarratives",
      "start" : 62,
      "length" : 2
    },
    {
      "activity" : "validate",
      "start" : 65,
      "length" : 7
    },
    {
      "activity" : "checkConformanceResources3",
      "start" : 86,
      "length" : 1
    },
    {
      "activity" : "validate",
      "start" : 86,
      "length" : 1
    },
    {
      "activity" : "generate1",
      "start" : 89,
      "length" : 10
    },
    {
      "activity" : "generate2",
      "start" : 104,
      "length" : 45
    },
    {
      "activity" : "generateValidationPack",
      "start" : 126,
      "length" : 1
    }]
  },
  {
    "name" : "fsh-generated/resources/ValueSet-jdv-ror-nature-capacite.json",
    "size" : 615,
    "processes" : [{
      "activity" : "load",
      "start" : 58,
      "length" : 4
    },
    {
      "activity" : "generateNarratives",
      "start" : 62,
      "length" : 2
    },
    {
      "activity" : "validate",
      "start" : 65,
      "length" : 6
    },
    {
      "activity" : "generate1",
      "start" : 89,
      "length" : 10
    },
    {
      "activity" : "generate2",
      "start" : 104,
      "length" : 36
    },
    {
      "activity" : "generateValidationPack",
      "start" : 126,
      "length" : 1
    }]
  },
  {
    "name" : "fsh-generated/resources/ValueSet-jdv-ror-niveau-dependance.json",
    "size" : 629,
    "processes" : [{
      "activity" : "loadResources",
      "start" : 57,
      "length" : 1
    },
    {
      "activity" : "load",
      "start" : 58,
      "length" : 9
    },
    {
      "activity" : "generateNarratives",
      "start" : 62,
      "length" : 179
    },
    {
      "activity" : "validate",
      "start" : 65,
      "length" : 704
    },
    {
      "activity" : "validate",
      "start" : 86,
      "length" : 1
    },
    {
      "activity" : "generate1",
      "start" : 89,
      "length" : 12
    },
    {
      "activity" : "generate2",
      "start" : 104,
      "length" : 569
    }]
  },
  {
    "name" : "fsh-generated/resources/ValueSet-jdv-ror-niveau-recours-orsan.json",
    "size" : 642,
    "processes" : [{
      "activity" : "loadResources",
      "start" : 57,
      "length" : 1
    },
    {
      "activity" : "load",
      "start" : 58,
      "length" : 4
    },
    {
      "activity" : "generateNarratives",
      "start" : 63,
      "length" : 3
    },
    {
      "activity" : "validate",
      "start" : 65,
      "length" : 9
    },
    {
      "activity" : "generate1",
      "start" : 89,
      "length" : 14
    },
    {
      "activity" : "generate2",
      "start" : 104,
      "length" : 44
    }]
  },
  {
    "name" : "fsh-generated/resources/ValueSet-jdv-ror-orientation-particuliere.json",
    "size" : 672,
    "processes" : [{
      "activity" : "load",
      "start" : 58,
      "length" : 4
    },
    {
      "activity" : "generateNarratives",
      "start" : 63,
      "length" : 3
    },
    {
      "activity" : "validate",
      "start" : 66,
      "length" : 7
    },
    {
      "activity" : "checkConformanceResources3",
      "start" : 86,
      "length" : 1
    },
    {
      "activity" : "validate",
      "start" : 86,
      "length" : 1
    },
    {
      "activity" : "generate1",
      "start" : 89,
      "length" : 14
    },
    {
      "activity" : "generate2",
      "start" : 104,
      "length" : 45
    },
    {
      "activity" : "generateValidationPack",
      "start" : 126,
      "length" : 1
    }]
  },
  {
    "name" : "fsh-generated/resources/ValueSet-jdv-ror-ouverture-annuelle.json",
    "size" : 632,
    "processes" : [{
      "activity" : "loadResources",
      "start" : 57,
      "length" : 1
    },
    {
      "activity" : "load",
      "start" : 58,
      "length" : 4
    },
    {
      "activity" : "checkR4R4B",
      "start" : 59,
      "length" : 1
    },
    {
      "activity" : "generateNarratives",
      "start" : 63,
      "length" : 2
    },
    {
      "activity" : "validate",
      "start" : 66,
      "length" : 7
    },
    {
      "activity" : "generate1",
      "start" : 89,
      "length" : 19
    },
    {
      "activity" : "generate2",
      "start" : 104,
      "length" : 46
    }]
  },
  {
    "name" : "fsh-generated/resources/ValueSet-jdv-ror-prestation-non-obligatoire.json",
    "size" : 713,
    "processes" : [{
      "activity" : "loadResources",
      "start" : 57,
      "length" : 1
    },
    {
      "activity" : "load",
      "start" : 58,
      "length" : 4
    },
    {
      "activity" : "generateNarratives",
      "start" : 63,
      "length" : 3
    },
    {
      "activity" : "validate",
      "start" : 66,
      "length" : 6
    },
    {
      "activity" : "validate",
      "start" : 86,
      "length" : 1
    },
    {
      "activity" : "generate1",
      "start" : 89,
      "length" : 13
    },
    {
      "activity" : "generate2",
      "start" : 104,
      "length" : 47
    }]
  },
  {
    "name" : "fsh-generated/resources/ValueSet-jdv-ror-profession-sante.json",
    "size" : 619,
    "processes" : [{
      "activity" : "load",
      "start" : 58,
      "length" : 4
    },
    {
      "activity" : "generateNarratives",
      "start" : 63,
      "length" : 2
    },
    {
      "activity" : "validate",
      "start" : 66,
      "length" : 5
    },
    {
      "activity" : "generateLogicalMaps",
      "start" : 86,
      "length" : 1
    },
    {
      "activity" : "generate1",
      "start" : 89,
      "length" : 12
    },
    {
      "activity" : "generate2",
      "start" : 104,
      "length" : 49
    },
    {
      "activity" : "generateValidationPack",
      "start" : 126,
      "length" : 1
    }]
  },
  {
    "name" : "fsh-generated/resources/ValueSet-jdv-ror-public-pris-en-charge.json",
    "size" : 645,
    "processes" : [{
      "activity" : "loadResources",
      "start" : 57,
      "length" : 1
    },
    {
      "activity" : "load",
      "start" : 58,
      "length" : 4
    },
    {
      "activity" : "load",
      "start" : 58,
      "length" : 1
    },
    {
      "activity" : "generateNarratives",
      "start" : 63,
      "length" : 3
    },
    {
      "activity" : "validate",
      "start" : 66,
      "length" : 7
    },
    {
      "activity" : "validate",
      "start" : 86,
      "length" : 1
    },
    {
      "activity" : "generate1",
      "start" : 89,
      "length" : 13
    },
    {
      "activity" : "generate2",
      "start" : 104,
      "length" : 76
    },
    {
      "activity" : "generateValidationPack",
      "start" : 126,
      "length" : 1
    }]
  },
  {
    "name" : "fsh-generated/resources/ValueSet-jdv-ror-qualification-pac.json",
    "size" : 622,
    "processes" : [{
      "activity" : "load",
      "start" : 58,
      "length" : 3
    },
    {
      "activity" : "generateNarratives",
      "start" : 63,
      "length" : 2
    },
    {
      "activity" : "validate",
      "start" : 66,
      "length" : 6
    },
    {
      "activity" : "checkConformanceResources3",
      "start" : 86,
      "length" : 1
    },
    {
      "activity" : "generate1",
      "start" : 89,
      "length" : 13
    },
    {
      "activity" : "generate2",
      "start" : 105,
      "length" : 41
    }]
  },
  {
    "name" : "fsh-generated/resources/ValueSet-jdv-ror-secteur-conventionnement.json",
    "size" : 701,
    "processes" : [{
      "activity" : "loadResources",
      "start" : 57,
      "length" : 1
    },
    {
      "activity" : "load",
      "start" : 58,
      "length" : 4
    },
    {
      "activity" : "checkR4R4B",
      "start" : 59,
      "length" : 1
    },
    {
      "activity" : "generateNarratives",
      "start" : 63,
      "length" : 3
    },
    {
      "activity" : "validate",
      "start" : 66,
      "length" : 7
    },
    {
      "activity" : "validate",
      "start" : 86,
      "length" : 1
    },
    {
      "activity" : "generate1",
      "start" : 89,
      "length" : 13
    },
    {
      "activity" : "generate2",
      "start" : 105,
      "length" : 41
    }]
  },
  {
    "name" : "fsh-generated/resources/ValueSet-jdv-ror-specialisation-pec.json",
    "size" : 694,
    "processes" : [{
      "activity" : "load",
      "start" : 58,
      "length" : 6
    },
    {
      "activity" : "generateNarratives",
      "start" : 63,
      "length" : 2
    },
    {
      "activity" : "validate",
      "start" : 66,
      "length" : 9
    },
    {
      "activity" : "generate1",
      "start" : 89,
      "length" : 13
    },
    {
      "activity" : "generate2",
      "start" : 105,
      "length" : 75
    },
    {
      "activity" : "generateValidationPack",
      "start" : 126,
      "length" : 1
    }]
  },
  {
    "name" : "fsh-generated/resources/ValueSet-jdv-ror-specialite-ordinale.json",
    "size" : 638,
    "processes" : [{
      "activity" : "loadResources",
      "start" : 57,
      "length" : 1
    },
    {
      "activity" : "load",
      "start" : 58,
      "length" : 8
    },
    {
      "activity" : "generateNarratives",
      "start" : 63,
      "length" : 2
    },
    {
      "activity" : "validate",
      "start" : 66,
      "length" : 5
    },
    {
      "activity" : "validate",
      "start" : 86,
      "length" : 1
    },
    {
      "activity" : "generate1",
      "start" : 89,
      "length" : 16
    },
    {
      "activity" : "generate2",
      "start" : 105,
      "length" : 65
    },
    {
      "activity" : "generateValidationPack",
      "start" : 126,
      "length" : 2
    }]
  },
  {
    "name" : "fsh-generated/resources/ValueSet-jdv-ror-statut-capacite.json",
    "size" : 615,
    "processes" : [{
      "activity" : "loadResources",
      "start" : 57,
      "length" : 1
    },
    {
      "activity" : "load",
      "start" : 58,
      "length" : 9
    },
    {
      "activity" : "generateNarratives",
      "start" : 63,
      "length" : 173
    },
    {
      "activity" : "validate",
      "start" : 66,
      "length" : 247
    },
    {
      "activity" : "checkConformanceResources3",
      "start" : 86,
      "length" : 1
    },
    {
      "activity" : "generate1",
      "start" : 89,
      "length" : 14
    },
    {
      "activity" : "generate2",
      "start" : 105,
      "length" : 441
    }]
  },
  {
    "name" : "fsh-generated/resources/ValueSet-jdv-ror-surspecialite-transversale.json",
    "size" : 690,
    "processes" : [{
      "activity" : "load",
      "start" : 58,
      "length" : 6
    },
    {
      "activity" : "load-configure",
      "start" : 59,
      "length" : 1
    },
    {
      "activity" : "generateNarratives",
      "start" : 63,
      "length" : 3
    },
    {
      "activity" : "validate",
      "start" : 66,
      "length" : 6
    },
    {
      "activity" : "validate",
      "start" : 86,
      "length" : 1
    },
    {
      "activity" : "generate1",
      "start" : 89,
      "length" : 13
    },
    {
      "activity" : "generate2",
      "start" : 105,
      "length" : 38
    },
    {
      "activity" : "generateValidationPack",
      "start" : 126,
      "length" : 1
    }]
  },
  {
    "name" : "fsh-generated/resources/ValueSet-jdv-ror-temporalite-accueil.json",
    "size" : 642,
    "processes" : [{
      "activity" : "loadResources",
      "start" : 57,
      "length" : 1
    },
    {
      "activity" : "load",
      "start" : 58,
      "length" : 4
    },
    {
      "activity" : "checkR4R4B",
      "start" : 59,
      "length" : 1
    },
    {
      "activity" : "generateNarratives",
      "start" : 63,
      "length" : 3
    },
    {
      "activity" : "validate",
      "start" : 66,
      "length" : 6
    },
    {
      "activity" : "validate",
      "start" : 86,
      "length" : 1
    },
    {
      "activity" : "generate1",
      "start" : 89,
      "length" : 13
    },
    {
      "activity" : "generate2",
      "start" : 105,
      "length" : 34
    },
    {
      "activity" : "generateValidationPack",
      "start" : 126,
      "length" : 1
    }]
  },
  {
    "name" : "fsh-generated/resources/ValueSet-jdv-ror-temporalite.json",
    "size" : 588,
    "processes" : [{
      "activity" : "load",
      "start" : 58,
      "length" : 7
    },
    {
      "activity" : "load",
      "start" : 58,
      "length" : 1
    },
    {
      "activity" : "generateNarratives",
      "start" : 63,
      "length" : 163
    },
    {
      "activity" : "validate",
      "start" : 66,
      "length" : 249
    },
    {
      "activity" : "generate1",
      "start" : 89,
      "length" : 13
    },
    {
      "activity" : "generate2",
      "start" : 105,
      "length" : 428
    }]
  },
  {
    "name" : "fsh-generated/resources/ValueSet-jdv-ror-type-crise.json",
    "size" : 579,
    "processes" : [{
      "activity" : "loadResources",
      "start" : 57,
      "length" : 1
    },
    {
      "activity" : "load",
      "start" : 58,
      "length" : 4
    },
    {
      "activity" : "generateNarratives",
      "start" : 63,
      "length" : 2
    },
    {
      "activity" : "validate",
      "start" : 66,
      "length" : 7
    },
    {
      "activity" : "checkConformanceResources3",
      "start" : 86,
      "length" : 1
    },
    {
      "activity" : "generate1",
      "start" : 89,
      "length" : 14
    },
    {
      "activity" : "generate2",
      "start" : 106,
      "length" : 31
    }]
  },
  {
    "name" : "fsh-generated/resources/ValueSet-jdv-ror-type-fermeture-capacite.json",
    "size" : 670,
    "processes" : [{
      "activity" : "load",
      "start" : 58,
      "length" : 6
    },
    {
      "activity" : "generateNarratives",
      "start" : 63,
      "length" : 2
    },
    {
      "activity" : "validate",
      "start" : 66,
      "length" : 6
    },
    {
      "activity" : "validate",
      "start" : 86,
      "length" : 1
    },
    {
      "activity" : "generate1",
      "start" : 89,
      "length" : 16
    },
    {
      "activity" : "generate2",
      "start" : 106,
      "length" : 32
    }]
  },
  {
    "name" : "fsh-generated/resources/ValueSet-jdv-ror-type-habitation.json",
    "size" : 613,
    "processes" : [{
      "activity" : "loadResources",
      "start" : 57,
      "length" : 1
    },
    {
      "activity" : "load",
      "start" : 58,
      "length" : 8
    },
    {
      "activity" : "generateNarratives",
      "start" : 63,
      "length" : 2
    },
    {
      "activity" : "validate",
      "start" : 66,
      "length" : 5
    },
    {
      "activity" : "validate",
      "start" : 86,
      "length" : 1
    },
    {
      "activity" : "generate1",
      "start" : 89,
      "length" : 13
    },
    {
      "activity" : "generate2",
      "start" : 106,
      "length" : 35
    },
    {
      "activity" : "generateValidationPack",
      "start" : 126,
      "length" : 1
    }]
  },
  {
    "name" : "fsh-generated/resources/ValueSet-jdv-ror-type-lit-supplementaire.json",
    "size" : 667,
    "processes" : [{
      "activity" : "load",
      "start" : 58,
      "length" : 11
    },
    {
      "activity" : "generateNarratives",
      "start" : 63,
      "length" : 2
    },
    {
      "activity" : "validate",
      "start" : 66,
      "length" : 5
    },
    {
      "activity" : "checkConformanceResources3",
      "start" : 86,
      "length" : 1
    },
    {
      "activity" : "generate1",
      "start" : 89,
      "length" : 10
    },
    {
      "activity" : "generate2",
      "start" : 106,
      "length" : 32
    }]
  },
  {
    "name" : "fsh-generated/resources/ValueSet-jdv-ror-type-organisation-interne.json",
    "size" : 677,
    "processes" : [{
      "activity" : "loadResources",
      "start" : 57,
      "length" : 1
    },
    {
      "activity" : "load",
      "start" : 58,
      "length" : 11
    },
    {
      "activity" : "checkR4R4B",
      "start" : 59,
      "length" : 1
    },
    {
      "activity" : "generateNarratives",
      "start" : 63,
      "length" : 2
    },
    {
      "activity" : "validate",
      "start" : 66,
      "length" : 5
    },
    {
      "activity" : "validate",
      "start" : 86,
      "length" : 1
    },
    {
      "activity" : "generate1",
      "start" : 89,
      "length" : 15
    },
    {
      "activity" : "generate2",
      "start" : 106,
      "length" : 32
    }]
  },
  {
    "name" : "fsh-generated/resources/ValueSet-jdv-ror-type-savoir-faire.json",
    "size" : 621,
    "processes" : [{
      "activity" : "loadResources",
      "start" : 57,
      "length" : 1
    },
    {
      "activity" : "load",
      "start" : 58,
      "length" : 11
    },
    {
      "activity" : "generateNarratives",
      "start" : 63,
      "length" : 2
    },
    {
      "activity" : "validate",
      "start" : 66,
      "length" : 5
    },
    {
      "activity" : "generate1",
      "start" : 89,
      "length" : 10
    },
    {
      "activity" : "generate2",
      "start" : 106,
      "length" : 37
    },
    {
      "activity" : "generateValidationPack",
      "start" : 126,
      "length" : 1
    }]
  },
  {
    "name" : "fsh-generated/resources/ValueSet-jdv-ror-type-source.json",
    "size" : 586,
    "processes" : [{
      "activity" : "load",
      "start" : 58,
      "length" : 19
    },
    {
      "activity" : "generateNarratives",
      "start" : 63,
      "length" : 166
    },
    {
      "activity" : "validate",
      "start" : 66,
      "length" : 1071
    },
    {
      "activity" : "validate",
      "start" : 86,
      "length" : 1
    },
    {
      "activity" : "generate1",
      "start" : 89,
      "length" : 9
    },
    {
      "activity" : "generate2",
      "start" : 106,
      "length" : 276
    }]
  },
  {
    "name" : "fsh-generated/resources/ValueSet-jdv-ror-type-tarif.json",
    "size" : 579,
    "processes" : [{
      "activity" : "loadResources",
      "start" : 57,
      "length" : 1
    },
    {
      "activity" : "load",
      "start" : 58,
      "length" : 6
    },
    {
      "activity" : "generateNarratives",
      "start" : 63,
      "length" : 2
    },
    {
      "activity" : "validate",
      "start" : 67,
      "length" : 4
    },
    {
      "activity" : "checkConformanceResources3",
      "start" : 86,
      "length" : 1
    },
    {
      "activity" : "generate1",
      "start" : 89,
      "length" : 10
    },
    {
      "activity" : "generate2",
      "start" : 106,
      "length" : 38
    },
    {
      "activity" : "generateValidationPack",
      "start" : 126,
      "length" : 1
    }]
  },
  {
    "name" : "fsh-generated/resources/ValueSet-jdv-ror-unite-prix.json",
    "size" : 580,
    "processes" : [{
      "activity" : "loadResources",
      "start" : 57,
      "length" : 1
    },
    {
      "activity" : "load",
      "start" : 58,
      "length" : 3
    },
    {
      "activity" : "scan",
      "start" : 59,
      "length" : 1
    },
    {
      "activity" : "generateNarratives",
      "start" : 63,
      "length" : 3
    },
    {
      "activity" : "validate",
      "start" : 67,
      "length" : 5
    },
    {
      "activity" : "validate",
      "start" : 86,
      "length" : 1
    },
    {
      "activity" : "generate1",
      "start" : 89,
      "length" : 10
    },
    {
      "activity" : "generate2",
      "start" : 106,
      "length" : 38
    }]
  },
  {
    "name" : "/input/includes/svg-interactive-styles.html",
    "size" : 2838,
    "processes" : [{
      "activity" : "validate",
      "start" : 86,
      "length" : 1
    }]
  },
  {
    "name" : "/input/includes/svg-interactive-script.html",
    "size" : 6346,
    "processes" : [{
      "activity" : "generate2",
      "start" : 106,
      "length" : 1
    }]
  },
  {
    "name" : "/fsh-generated/includes/fsh-link-references.md",
    "size" : 6026,
    "processes" : [{
      "activity" : "validate",
      "start" : 86,
      "length" : 1
    },
    {
      "activity" : "generate2",
      "start" : 106,
      "length" : 1
    }]
  },
  {
    "name" : "/fsh-generated/includes/menu.xml",
    "size" : 2389
  },
  {
    "name" : "/input/data/features.yml",
    "size" : 164
  },
  {
    "name" : "/input/pagecontent/index.md",
    "size" : 4585,
    "processes" : [{
      "activity" : "generate2",
      "start" : 106,
      "length" : 1
    }]
  },
  {
    "name" : "/input/pagecontent/fonctionnalites-ror.md",
    "size" : 3290,
    "processes" : [{
      "activity" : "validate",
      "start" : 86,
      "length" : 1
    }]
  },
  {
    "name" : "/input/pagecontent/structure.md",
    "size" : 6124,
    "processes" : [{
      "activity" : "generate2",
      "start" : 106,
      "length" : 1
    }]
  },
  {
    "name" : "/input/pagecontent/classes-communes.md",
    "size" : 4399,
    "processes" : [{
      "activity" : "validate",
      "start" : 86,
      "length" : 1
    }]
  },
  {
    "name" : "/input/pagecontent/avantages-ml.md",
    "size" : 3526,
    "processes" : [{
      "activity" : "generate2",
      "start" : 106,
      "length" : 1
    }]
  },
  {
    "name" : "/input/pagecontent/ressources-operationnelles.md",
    "size" : 3952,
    "processes" : [{
      "activity" : "validate",
      "start" : 86,
      "length" : 1
    }]
  },
  {
    "name" : "/input/pagecontent/tarif.md",
    "size" : 4583,
    "processes" : [{
      "activity" : "generate2",
      "start" : 106,
      "length" : 1
    }]
  },
  {
    "name" : "/input/pagecontent/change-log.md",
    "size" : 222
  },
  {
    "name" : "/input/pagecontent/organisation.md",
    "size" : 4148,
    "processes" : [{
      "activity" : "validate",
      "start" : 86,
      "length" : 1
    }]
  },
  {
    "name" : "/input/pagecontent/professionnel.md",
    "size" : 5763
  },
  {
    "name" : "/input/pagecontent/offre-operationnelle.md",
    "size" : 6381,
    "processes" : [{
      "activity" : "validate",
      "start" : 86,
      "length" : 1
    },
    {
      "activity" : "generate2",
      "start" : 106,
      "length" : 1
    },
    {
      "activity" : "makeDependencies",
      "start" : 109,
      "length" : 1
    }]
  },
  {
    "name" : "/template/config",
    "size" : 0
  },
  {
    "name" : "/template/config/_config.yml",
    "size" : 140,
    "processes" : [{
      "activity" : "validate",
      "start" : 86,
      "length" : 1
    }]
  },
  {
    "name" : "/input/images",
    "size" : 0,
    "processes" : [{
      "activity" : "generate2",
      "start" : 106,
      "length" : 1
    }]
  },
  {
    "name" : "/input/images/anImage.png",
    "size" : 36288,
    "processes" : [{
      "activity" : "validate",
      "start" : 86,
      "length" : 1
    }]
  },
  {
    "name" : "/input/images/ci-sis-logo.png",
    "size" : 61365,
    "processes" : [{
      "activity" : "generate2",
      "start" : 106,
      "length" : 1
    }]
  },
  {
    "name" : "/temp/pages/_includes/artifacts.xml",
    "size" : 58662,
    "processes" : [{
      "activity" : "generate2",
      "start" : 106,
      "length" : 2
    }]
  }]
}
